wordle_benchmark/__init__.py
wordle_benchmark/agent/__init__.py
wordle_benchmark/agent/wordle_agent.py
wordle_benchmark/benchmarker/__init__.py
wordle_benchmark/benchmarker/wordle_benchmarker.py
wordle_benchmark/dictionary/__init__.py
wordle_benchmark/dictionary/wordle_dictionary.py
wordle_benchmark/game/__init__.py
wordle_benchmark/game/wordle_game.py
wordle_benchmark/game/wordle_words.py
wordle_benchmark-1.0.3.dist-info/LICENSE
wordle_benchmark-1.0.3.dist-info/METADATA
wordle_benchmark-1.0.3.dist-info/WHEEL
wordle_benchmark-1.0.3.dist-info/top_level.txt
wordle_benchmark-1.0.3.dist-info/RECORD
