Metadata-Version: 2.1
Name: wordle-benchmark
Version: 1.0.3
Summary: Wordle package to benchmark agents. The package is intended         to support replicable heuristic evaluation of Wordle playing software.
Home-page: UNKNOWN
Author: Peter Bryan
Author-email: peterbbryan@gmail.com
License: MIT
Platform: UNKNOWN
Requires-Python: >3.7
License-File: LICENSE
Requires-Dist: numpy
Requires-Dist: requests
